rustuya/__init__.py
rustuya/rustuya.abi3.so
rustuya-0.2.0.dist-info/METADATA
rustuya-0.2.0.dist-info/WHEEL
rustuya-0.2.0.dist-info/RECORD
