Metadata-Version: 2.4
Name: rustuya
Version: 0.2.0
Classifier: Intended Audience :: Developers
Classifier: License :: OSI Approved :: MIT License
Classifier: Programming Language :: Rust
Classifier: Programming Language :: Python :: 3
Summary: A fast and concurrent Tuya Local API implementation in Rust
Keywords: tuya,iot,smart-home,automation
Home-Page: https://github.com/3735943886/rustuya
Author: 3735943886
License: MIT
Requires-Python: >=3.7
Project-URL: Homepage, https://github.com/3735943886/rustuya
Project-URL: Repository, https://github.com/3735943886/rustuya
